[{"id":"8b46f999-6db0-413b-951a-9137f67c15ad","avatarName":"jjjjjj","childAge":15,"skinColor":"#000000","hairstyle":"short","headShape":"round","upperClothing":"shirt","lowerClothing":"pants","createdAt":"2024-04-24T08:36:10.140Z"},{"id":"7b56c3c7-8a0a-4cd8-8143-fb976ab7888b","avatarName":"kk;","childAge":15,"skinColor":"#000000","hairstyle":"short","headShape":"round","upperClothing":"shirt","lowerClothing":"pants","createdAt":"2024-04-24T08:41:52.429Z"},{"id":"11d0f37e-1465-4ae5-8dd4-78b08110e4f0","avatarName":"mimjio","childAge":15,"skinColor":"#000000","hairstyle":"short","headShape":"round","upperClothing":"shirt","lowerClothing":"pants","createdAt":"2024-04-24T08:42:36.148Z"},{"id":"26514f46-a742-4f38-a5ca-a592bb4b529a","avatarName":"Mark","childAge":12,"skinColor":"#0000ff","hairstyle":"short","headShape":"oval","upperClothing":"jacket","lowerClothing":"shorts","createdAt":"2024-04-24T08:55:02.285Z"},{"id":"9130f113-c05a-4382-bcb6-77133564e593","avatarName":"Mark","childAge":12,"skinColor":"#0000ff","hairstyle":"short","headShape":"oval","upperClothing":"jacket","lowerClothing":"shorts","createdAt":"2024-04-24T08:55:02.372Z"},{"id":"c5b72d75-1a94-4d64-91cf-63410f489a01","avatarName":"lll","childAge":5,"skinColor":"#000000","hairstyle":"short","headShape":"round","upperClothing":"shirt","lowerClothing":"pants","createdAt":"2024-04-24T12:23:36.806Z"}]